<step title="Incoming Request" date="2026-01-02T13:12:59.531" instance="582035" url="/api/deployments/latest?deployer=OneDeploy&amp;time=2026-01-02_13-09-42Z" method="GET" type="request" pid="768,1,28" Host="inmoleads-crm.scm.azurewebsites.net" User-Agent="GITHUBACTIONS_DeployWebAppToAzure_8c4a1760a1487c4c170ecae70de8336f3fc7058c6ca8147ceb3e092f7bc77fce" Authorization="Bas..." Content-Type="application/json; charset=utf-8" Cookie="ARRAffinity=58203501dbaee15c4cd518c7b7697694be4cbec1031fdad6f0532854f9ed447a;Path=/;HttpOnly;Secure;Domain=inmoleads-crm.scm.azurewebsites.net; ARRAffinitySameSite=58203501dbaee15c4cd518c7b7697694be4cbec1031fdad6f0532854f9ed447a;Path=/;HttpOnly;SameSite=None;Secure;Domain=inmoleads-crm.scm.azurewebsites.net" Content-Length="0" X-ARR-LOG-ID="24a9056e-0bac-468b-a4b6-579e3047fdb0" CLIENT-IP="172.182.212.6:2106" X-SITE-DEPLOYMENT-ID="inmoleads-crm" WAS-DEFAULT-HOSTNAME="inmoleads-crm.scm.azurewebsites.net" X-Forwarded-Proto="https" X-AppService-Proto="https" X-Forwarded-TlsVersion="1.3" X-WAWS-Unencoded-URL="/api/deployments/latest?deployer=OneDeploy&amp;time=2026-01-02_13-09-42Z" X-Client-IP="172.182.212.6" X-Client-Port="2106" >
  <step title="Cleanup Xml Logs" date="2026-01-02T13:12:59.551" >
    <step title="Cleanup Infos" date="2026-01-02T13:12:59.860" totalFiles="4580" totalCleanup="4420" /><!-- duration: 66ms -->
  </step><!-- duration: 392ms -->
  <step title="DeploymentService.GetResult" date="2026-01-02T13:12:59.962" >
    <step title="DeploymentService.GetLatestDeployment" date="2026-01-02T13:12:59.971" >
      <step title="DeploymentManager.GetResults" date="2026-01-02T13:12:59.981" /><!-- duration: 1338ms -->
    </step><!-- duration: 1387ms -->
  </step><!-- duration: 1406ms -->
  <step title="Outgoing response" date="2026-01-02T13:13:01.378" type="response" statusCode="202" statusText="Accepted" /><!-- duration: 11ms -->
</step><!-- duration: 1875ms -->
