<step title="Incoming Request" date="2026-01-11T21:19:12.149" instance="949b23" url="/api/deployments/latest?deployer=OneDeploy&amp;time=2026-01-11_21-10-21Z" method="GET" type="request" pid="774,1,7" Host="inmoleads-crm.scm.azurewebsites.net" User-Agent="GITHUBACTIONS_DeployWebAppToAzure_8c4a1760a1487c4c170ecae70de8336f3fc7058c6ca8147ceb3e092f7bc77fce" Authorization="Bas..." Content-Type="application/json; charset=utf-8" Cookie="ARRAffinity=949b2381a2836c2e50a9dff5453e2f181ebc7f1a608d18b1d30a7ddca97c246b;Path=/;HttpOnly;Secure;Domain=inmoleads-crm.scm.azurewebsites.net; ARRAffinitySameSite=949b2381a2836c2e50a9dff5453e2f181ebc7f1a608d18b1d30a7ddca97c246b;Path=/;HttpOnly;SameSite=None;Secure;Domain=inmoleads-crm.scm.azurewebsites.net" Content-Length="0" X-ARR-LOG-ID="ed84d67e-4601-4a6f-8e42-8986701fcdfe" CLIENT-IP="135.232.185.17:47112" X-SITE-DEPLOYMENT-ID="inmoleads-crm" WAS-DEFAULT-HOSTNAME="inmoleads-crm.scm.azurewebsites.net" X-Forwarded-Proto="https" X-AppService-Proto="https" X-Forwarded-TlsVersion="1.3" X-WAWS-Unencoded-URL="/api/deployments/latest?deployer=OneDeploy&amp;time=2026-01-11_21-10-21Z" X-Client-IP="135.232.185.17" X-Client-Port="47112" >
  <step title="Cleanup Xml Logs" date="2026-01-11T21:19:12.151" >
    <step title="Cleanup Infos" date="2026-01-11T21:19:12.559" totalFiles="10129" totalCleanup="9969" /><!-- duration: 98ms -->
  </step><!-- duration: 519ms -->
  <step title="DeploymentService.GetResult" date="2026-01-11T21:19:12.686" >
    <step title="DeploymentService.GetLatestDeployment" date="2026-01-11T21:19:12.687" >
      <step title="DeploymentManager.GetResults" date="2026-01-11T21:19:12.698" /><!-- duration: 683ms -->
    </step><!-- duration: 702ms -->
  </step><!-- duration: 714ms -->
  <step title="Outgoing response" date="2026-01-11T21:19:13.420" type="response" statusCode="202" statusText="Accepted" /><!-- duration: 8ms -->
</step><!-- duration: 1280ms -->
